logiclm/ai.py
logiclm/logiclm.py
logiclm/olap.py
logiclm/run_tests.py
logiclm/schema.py
logiclm/server.py
logiclm-1.0.1.dist-info/LICENSE
logiclm-1.0.1.dist-info/METADATA
logiclm-1.0.1.dist-info/WHEEL
logiclm-1.0.1.dist-info/top_level.txt
logiclm-1.0.1.dist-info/RECORD
