Metadata-Version: 2.1
Name: logiclm
Version: 1.0.1
Summary: LogicLM
Home-page: https://github.com/google/LogicLM
Author: Google LLC
Author-email: logica@evgeny.ninja
License: UNKNOWN
Platform: UNKNOWN
Classifier: Topic :: Database
Classifier: License :: OSI Approved :: Apache Software License
Requires-Python: >=3.0
License-File: LICENSE
